altair_data_server/__init__.py
altair_data_server/_altair_server.py
altair_data_server/_background_server.py
altair_data_server/_provide.py
altair_data_server/tests/__init__.py
altair_data_server/tests/test_altair_server.py
altair_data_server/tests/test_entrypoint.py
altair_data_server/tests/test_provider.py
altair_data_server-0.4.0.dist-info/LICENSE
altair_data_server-0.4.0.dist-info/METADATA
altair_data_server-0.4.0.dist-info/WHEEL
altair_data_server-0.4.0.dist-info/entry_points.txt
altair_data_server-0.4.0.dist-info/top_level.txt
altair_data_server-0.4.0.dist-info/RECORD
