Metadata-Version: 2.1
Name: altair-data-server
Version: 0.4.0
Summary: A background data server for Altair charts.
Home-page: http://github.com/altair-viz/altair_data_server/
Author: Jake VanderPlas
Author-email: jakevdp@google.com
License: BSD 3-clause
Download-URL: http://github.com/altair-viz/altair_data_server/
Platform: UNKNOWN
Classifier: Development Status :: 5 - Production/Stable
Classifier: Environment :: Console
Classifier: Intended Audience :: Science/Research
Classifier: License :: OSI Approved :: BSD License
Classifier: Natural Language :: English
Classifier: Programming Language :: Python :: 3.6
Classifier: Programming Language :: Python :: 3.7
Classifier: Programming Language :: Python :: 3.8
Requires-Python: >=3.6
Requires-Dist: altair
Requires-Dist: portpicker
Requires-Dist: tornado
